ChinaIDCard/__init__.py
ChinaIDCard/main.py
ChinaIDCard-0.0.1.dist-info/METADATA
ChinaIDCard-0.0.1.dist-info/WHEEL
ChinaIDCard-0.0.1.dist-info/top_level.txt
ChinaIDCard-0.0.1.dist-info/RECORD
