Metadata-Version: 2.1
Name: ChinaIDCard
Version: 0.0.1
Summary: 中国身份证效验
Home-page: https://github.com/Moxin1044/eShenfenKu
Author: Moxin
Author-email: Moxin1044@gmail.com
License: MIT License
